Workbook

Sheet Financials
B1: 1 | C1: 2 | D1: 3 | E1: 4 | F1: 5 | G1: 6 | H1: 7 | I1: 8 | J1: 9 | K1: 10 | L1: 11 | M1: 12
A2: United Health Income Statement - 10K
B3: 2014 | C3: 2015 | D3: 2016 | E3: 2017 | F3: 2018 | G3: 2019 | H3: 2020 | I3: 2021 | J3: 2022 | K3: 2023 | L3: 2024 | M3: 2025 | N3: 2026 | O3: 2027 | P3: 2028 | Q3: 2029 | R3: 2030 | S3: 2031 | T3: 2032 | U3: 2033 | V3: 2034
A4: Total revenues | B4: 130474 | C4: 157107 | D4: 184840 | E4: 201159 | F4: 226247 | G4: 242155 | H4: 257141 | I4: 287597 | J4: 324162 | K4: 371622 | L4: 400278 | M4: =FS_Forecast!M4 -> 447567 | N4: 439000 | O4: =N4*(1+O5) -> 445083.98 | P4: =O4*(1+P5) -> 465940.05 | Q4: =P4*(1+Q5) -> 503149.44 | R4: =Q4*(1+R5) -> 540542.86 | S4: =R4*(1+S5) -> 577720.72 | T4: =S4*(1+T5) -> 614255.04 | U4: =T4*(1+U5) -> 649696.78 | V4: =U4*(1+V5) -> 683545.98
A5: % increase in revenue | B5: -% | C5: =(C4/B4)-1 -> 0.20412496 | D5: =(D4/C4)-1 -> 0.17652301 | E5: =(E4/D4)-1 -> 0.088287167 | F5: =(F4/E4)-1 -> 0.12471726 | G5: =(G4/F4)-1 -> 0.070312535 | H5: =(H4/G4)-1 -> 0.061885982 | I5: =(I4/H4)-1 -> 0.11844086 | J5: =(J4/I4)-1 -> 0.12713971 | ... N5: =(N4/M4)-1 -> -0.019141268 | O5: =N5+3.3% -> 0.013858732 | P5: =O5+3.3% -> 0.046858732 | Q5: =P5+3.3% -> 0.079858732 | R5: =Q5-R6 -> 0.074318732 | S5: =R5-R6 -> 0.068778732 | T5: =S5-R6 -> 0.063238732 | U5: =T5-R6 -> 0.057698732 | V5: 0.0521
D6: 1 | E6: 2 | F6: 3 | I6: 4 | J6: 5 | K6: 6 | L6: 7 | R6: =2.77/500 -> 0.00554
A7: Total Cost Of Goods Sold | B7: =FS_Forecast!B7 -> 118722 | C7: =FS_Forecast!C7 -> 146068 | D7: =FS_Forecast!D7 -> 171910 | E7: =FS_Forecast!E7 -> 185950 | F7: =FS_Forecast!F7 -> 208903 | G7: =FS_Forecast!G7 -> 222470 | H7: =FS_Forecast!H7 -> 234736 | I7: =FS_Forecast!I7 -> 260524 | ... M7: =FS_Forecast!M7 -> 424242 | N7: 399182.7 | O7: 404686 | P7: 423619.81 | Q7: 457418.91 | R7: 491380.63 | S7: 525141.63 | T7: 558312.94 | U7: 590486.52 | V7: 621250.87
A8: % of total revenue | B8: =B7/B4 -> 0.90992841 | C8: =C7/C4 -> 0.92973579 | D8: =D7/D4 -> 0.93004761 | E8: =E7/E4 -> 0.92439314 | F8: =F7/F4 -> 0.92334042 | G8: =G7/G4 -> 0.91870909 | H8: =H7/H4 -> 0.91286882 | I8: =I7/I4 -> 0.9058648 | ... L8: =L7/L4 -> 0.91933856 | M8: =FS_Forecast!M8 -> 0.9478849 | N8: 0.9093 | O8: 0.9093 | P8: 0.9093 | Q8: 0.9093 | R8: 0.9093 | S8: 0.9093 | T8: 0.9093 | U8: 0.9093 | V8: 0.9093 | Y8: Total Cost Of Goods Sold | Z8: 118722 | AA8: 144393 | AB8: 169855 | AC8: 183705 | AD8: 206475 | AE8: 219750 | AF8: 231845 | AG8: 260524 | AH8: 292327 | AI8: 335292 | AJ8: 363892 | AK8: 406985.27 | AL8: 399182.7 | AM8: 404686 | AN8: 423619.81 | AO8: 457418.91 | AP8: 491380.63 | AQ8: 525141.63 | AR8: 558312.94 | AS8: 590486.52 | AT8: 621250.87
A9: Gross Profit | B9: =B4-B7 -> 11752 | C9: =C4-C7 -> 11039 | D9: =D4-D7 -> 12930 | E9: =E4-E7 -> 15209 | F9: =F4-F7 -> 17344 | G9: =G4-G7 -> 19685 | H9: =H4-H7 -> 22405 | I9: =I4-I7 -> 27073 | ... V9: =V4-V7 -> 62295.114 | Y9: % of total revenue | Z9: 0.90992841 | AA9: 0.91907426 | AB9: 0.91892989 | AC9: 0.91323282 | AD9: 0.91260879 | AE9: 0.90747662 | AF9: 0.90162596 | AG9: 0.9058648 | AH9: 0.90179293 | AI9: 0.90223937 | AJ9: 0.90909818 | AK9: 0.90926109 | AL9: 0.9093 | AM9: 0.9093 | AN9: 0.9093 | AO9: 0.9093 | AP9: 0.9093 | AQ9: 0.9093 | AR9: 0.9093 | AS9: 0.9093 | AT9: 0.9093
A10: % of total revenue | B10: =B9/B4 -> 0.090071585 | C10: =C9/C4 -> 0.070264215 | D10: =D9/D4 -> 0.069952391 | E10: =E9/E4 -> 0.075606858 | F10: =F9/F4 -> 0.07665958 | G10: =G9/G4 -> 0.081290909 | H10: =H9/H4 -> 0.087131185 | I10: =I9/I4 -> 0.094135196 | ... L10: =L9/L4 -> 0.08066144 | M10: =FS_Forecast!M10 -> 0.052115102 | N10: =N9/N4 -> 0.0907 | O10: =O9/O4 -> 0.090764857 | P10: =P9/P4 -> 0.090827666 | Q10: =Q9/Q4 -> 0.090888551 | R10: =R9/R4 -> 0.090949746 | S10: =S9/S4 -> 0.091011253 | T10: =T9/T4 -> 0.091073078 | U10: =U9/U4 -> 0.091135221 | V10: =V9/V4 -> 0.091135221 | Y10: Gross Profit | Z10: 11752 | AA10: 12714 | AB10: 14985 | AC10: 17454 | AD10: 19772 | AE10: 22405 | AF10: 25296 | AG10: 27073 | AH10: 31835 | AI10: 36330 | AJ10: 36386 | AK10: 40614.735 | AL10: 39817.3 | AM10: 40366.238 | AN10: 42254.829 | AO10: 45626.191 | AP10: 49013.772 | AQ10: 52381.333 | AR10: 55690.074 | AS10: 58899.293 | AT10: 61967.946
A11: Depreciation and amortization | B11: =H311 -> 1478 | C11: =I311 -> 1693 | D11: =B311 -> 2055 | E11: =C311 -> 2245 | F11: =D311 -> 2428 | G11: 2720 | H11: 2891 | I11: 3103 | J11: 3400 | K11: 3972 | L11: 4099 | M11: =FS_Forecast!M11 -> 4361 | N11: =N4*N12 -> 4785.1 | O11: =O4*O12 -> 4851.4154 | P11: =P4*P12 -> 5078.7466 | Q11: =Q4*Q12 -> 5484.3289 | R11: =R4*R12 -> 5891.9172 | S11: =S4*S12 -> 6297.1558 | T11: =T4*T12 -> 6695.38 | U11: =U4*U12 -> 7081.6949 | V11: =V4*V12 -> 7450.6512 | Y11: % of total revenue | Z11: 0.090071585 | AA11: 0.080925739 | AB11: 0.081070115 | AC11: 0.086767184 | AD11: 0.087391214 | AE11: 0.092523384 | AF11: 0.098374044 | AG11: 0.094135196 | AH11: 0.098207069 | AI11: 0.097760628 | AJ11: 0.090901823 | AK11: 0.090738907 | AL11: 0.0907 | AM11: 0.0907 | AN11: 0.0907 | AO11: 0.0907 | AP11: 0.0907 | AQ11: 0.0907 | AR11: 0.0907 | AS11: 0.0907 | AT11: 0.0907
A12: =A10 -> % of total revenue | B12: =B11/B4 -> 0.011327927 | C12: =C11/C4 -> 0.010776095 | D12: =D11/D4 -> 0.011117723 | E12: =E11/E4 -> 0.011160326 | F12: =F11/F4 -> 0.010731634 | G12: =G11/G4 -> 0.011232475 | H12: =H11/H4 -> 0.011242859 | I12: =I11/I4 -> 0.010789403 | ... L12: =L11/L4 -> 0.010240383 | M12: =FS_Forecast!M12 -> 0.0097437925 | N12: 0.0109 | O12: 0.0109 | P12: 0.0109 | Q12: 0.0109 | R12: 0.0109 | S12: 0.0109 | T12: 0.0109 | U12: 0.0109 | V12: 0.0109 | Y12: Depreciation and amortization | Z12: 1478 | AA12: 1693 | AB12: 2055 | AC12: 2245 | AD12: 2428 | AE12: 2720 | AF12: 2891 | AG12: 3103 | AH12: 3400 | AI12: 3972 | AJ12: 4099 | AK12: 4874.5955 | AL12: 4785.1 | AM12: 4851.0694 | AN12: 5078.0335 | AO12: 5483.1916 | AP12: 5890.299 | AQ12: 6295.0003 | AR12: 6692.6329 | AS12: 7078.3054 | AT12: 7447.0851
A13: EBIT | B13: =B9-B11 -> 10274 | C13: =C9-C11 -> 9346 | D13: =D9-D11 -> 10875 | E13: =E9-E11 -> 12964 | F13: =F9-F11 -> 14916 | G13: =G9-G11 -> 16965 | H13: =H9-H11 -> 19514 | I13: =I9-I11 -> 23970 | ... V13: =V9-V11 -> 54844.463 | Y13: % of total revenue | Z13: 0.011327927 | AA13: 0.010776095 | AB13: 0.011117723 | AC13: 0.011160326 | AD13: 0.010731634 | AE13: 0.011232475 | AF13: 0.011242859 | AG13: 0.010789403 | AH13: 0.010488583 | AI13: 0.01068828 | AJ13: 0.010240383 | AK13: 0.010890517 | AL13: 0.0109 | AM13: 0.0109 | AN13: 0.0109 | AO13: 0.0109 | AP13: 0.0109 | AQ13: 0.0109 | AR13: 0.0109 | AS13: 0.0109 | AT13: 0.0109
A14: % of total revenue | B14: =B13/B4 -> 0.078743658 | C14: =C13/C4 -> 0.05948812 | D14: =D13/D4 -> 0.058834668 | E14: =E13/E4 -> 0.064446532 | F14: =F13/F4 -> 0.065927946 | G14: =G13/G4 -> 0.070058434 | H14: =H13/H4 -> 0.075888326 | I14: =I13/I4 -> 0.083345793 | ... L14: =L13/L4 -> 0.070421057 | M14: =FS_Forecast!M14 -> 0.04237131 | N14: =N13/N4 -> 0.0798 | O14: =O13/O4 -> 0.079864857 | P14: =P13/P4 -> 0.079927666 | Q14: =Q13/Q4 -> 0.079988551 | R14: =R13/R4 -> 0.080049746 | S14: =S13/S4 -> 0.080111253 | T14: =T13/T4 -> 0.080173078 | U14: =U13/U4 -> 0.080235221 | V14: =V13/V4 -> 0.080235221 | Y14: EBIT | Z14: 10274 | AA14: 11021 | AB14: 12930 | AC14: 15209 | AD14: 17344 | AE14: 19685 | AF14: 22405 | AG14: 23970 | AH14: 28435 | AI14: 32358 | AJ14: 32287 | AK14: 35740.139 | AL14: 35032.2 | AM14: 35515.168 | AN14: 37176.796 | AO14: 40142.999 | AP14: 43123.473 | AQ14: 46086.332 | AR14: 48997.441 | AS14: 51820.988 | AT14: 54520.861
A15: Interest expense | B15: =H315 -> -618 | C15: =I315 -> -790 | D15: =B315 -> -1067 | E15: =C315 -> -1186 | F15: =D315 -> -1400 | G15: -1704 | H15: -1663 | I15: -1660 | J15: -2092 | K15: -3246 | L15: -3906 | M15: =FS_Forecast!M15 -> -4002 | N15: =-N4*N16 -> -4390 | O15: =-O4*O16 -> -4450.8398 | P15: =-P4*P16 -> -4659.4005 | Q15: =-Q4*Q16 -> -5031.4944 | R15: =-R4*R16 -> -5405.4286 | S15: =-S4*S16 -> -5777.2072 | T15: =-T4*T16 -> -6142.5504 | U15: =-U4*U16 -> -6496.9678 | V15: =-V4*V16 -> -6835.4598 | Y15: % of total revenue | Z15: 0.078743658 | AA15: 0.070149643 | AB15: 0.069952391 | AC15: 0.075606858 | AD15: 0.07665958 | AE15: 0.081290909 | AF15: 0.087131185 | AG15: 0.083345793 | AH15: 0.087718486 | AI15: 0.087072348 | AJ15: 0.08066144 | AK15: 0.07984839 | AL15: 0.0798 | AM15: 0.0798 | AN15: 0.0798 | AO15: 0.0798 | AP15: 0.0798 | AQ15: 0.0798 | AR15: 0.0798 | AS15: 0.0798 | AT15: 0.0798
A16: % of total revenue | B16: =-B15/B4 -> 0.0047365759 | C16: =-C15/C4 -> 0.0050284201 | D16: =-D15/D4 -> 0.0057725601 | E16: =-E15/E4 -> 0.0058958336 | F16: =-F15/F4 -> 0.0061879274 | G16: =-G15/G4 -> 0.0070368153 | H16: =-H15/H4 -> 0.0064672689 | I16: =-I15/I4 -> 0.0057719656 | ... L16: =-L15/L4 -> 0.009758218 | M16: =FS_Forecast!M16 -> 0.008941678 | N16: 0.01 | O16: 0.01 | P16: 0.01 | Q16: 0.01 | R16: 0.01 | S16: 0.01 | T16: 0.01 | U16: 0.01 | V16: 0.01 | Y16: Interest expense | Z16: -618 | AA16: -790 | AB16: -1067 | AC16: -1186 | AD16: -1400 | AE16: -1704 | AF16: -1663 | AG16: -1660 | AH16: -2092 | AI16: -3246 | AJ16: -3906 | AK16: -4476 | AL16: -4390 | AM16: -4450.5224 | AN16: -4658.7464 | AO16: -5030.451 | AP16: -5403.944 | AQ16: -5775.2296 | AR16: -6140.0302 | AS16: -6493.8581 | AT16: -6832.1881
A17: Loss on sale of subsidiary and subsidiaries held for sale | B17: 0 | C17: 0 | D17: 0 | E17: 0 | F17: 0 | G17: 0 | H17: 0 | I17: 0 | J17: 0 | K17: 0 | L17: -8310 | M17: =FS_Forecast!M17 -> 0 | N17: 0 | O17: 0 | P17: 0 | Q17: 0 | R17: 0 | S17: 0 | T17: 0 | U17: 0 | V17: 0 | Y17: % of total revenue | Z17: 0.0047365759 | AA17: 0.0050284201 | AB17: 0.0057725601 | AC17: 0.0058958336 | AD17: 0.0061879274 | AE17: 0.0070368153 | AF17: 0.0064672689 | AG17: 0.0057719656 | AH17: 0.0064535633 | AI17: 0.008734682 | AJ17: 0.009758218 | AK17: 0.01 | AL17: 0.01 | AM17: 0.01 | AN17: 0.01 | AO17: 0.01 | AP17: 0.01 | AQ17: 0.01 | AR17: 0.01 | AS17: 0.01 | AT17: 0.01
A18: Earnings Before Tax | B18: =SUM(B13,B15,B17) -> 9656 | C18: =SUM(C13,C15,C17) -> 8556 | D18: =SUM(D13,D15,D17) -> 9808 | E18: =SUM(E13,E15,E17) -> 11778 | F18: =SUM(F13,F15,F17) -> 13516 | G18: =SUM(G13,G15,G17) -> 15261 | H18: =SUM(H13,H15,H17) -> 17851 | I18: =SUM(I13,I15,I17) -> 22310 | ... V18: =SUM(V13,V15,V17) -> 48009.003 | Y18: Loss on sale of subsidiary and subsidiaries held for sale | Z18: 0 | AA18: 0 | AB18: 0 | AC18: 0 | AD18: 0 | AE18: 0 | AF18: 0 | AG18: 0 | AH18: 0 | AI18: 0 | AJ18: -8310 | AK18: 0 | AL18: 0 | AM18: 0 | AN18: 0 | AO18: 0 | AP18: 0 | AQ18: 0 | AR18: 0 | AS18: 0 | AT18: 0
A19: % of total revenue | B19: =B18/B4 -> 0.074007082 | C19: =C18/C4 -> 0.054459699 | D19: =D18/D4 -> 0.053062108 | E19: =E18/E4 -> 0.058550699 | F19: =F18/F4 -> 0.059740019 | G19: =G18/G4 -> 0.063021618 | H19: =H18/H4 -> 0.069421057 | I19: =I18/I4 -> 0.077573827 | ... L19: =L18/L4 -> 0.039902268 | M19: =FS_Forecast!M19 -> 0.033429632 | N19: =N18/N4 -> 0.0698 | O19: =O18/O4 -> 0.069864857 | P19: =P18/P4 -> 0.069927666 | Q19: =Q18/Q4 -> 0.069988551 | R19: =R18/R4 -> 0.070049746 | S19: =S18/S4 -> 0.070111253 | T19: =T18/T4 -> 0.070173078 | U19: =U18/U4 -> 0.070235221 | V19: =V18/V4 -> 0.070235221 | Y19: Earnings Before Tax | Z19: 9656 | AA19: 10231 | AB19: 11863 | AC19: 14023 | AD19: 15944 | AE19: 17981 | AF19: 20742 | AG19: 22310 | AH19: 26343 | AI19: 29112 | AJ19: 20071 | AK19: 31264.139 | AL19: 30642.2 | AM19: 31064.646 | AN19: 32518.05 | AO19: 35112.548 | AP19: 37719.529 | AQ19: 40311.103 | AR19: 42857.411 | AS19: 45327.13 | AT19: 47688.673
A20: Provision for income taxes | B20: =H317 -> -4037 | C20: =I317 -> -4363 | D20: =B317 -> -4790 | E20: =C317 -> -3200 | F20: =D317 -> -3562 | G20: -3742 | H20: -4973 | I20: -4578 | J20: -4829 | K20: -5968 | L20: -5704 | M20: =FS_Forecast!M20 -> -1890 | N20: =-N21*N13 -> -6190.1897 | O20: =-O21*O13 -> -6281.0787 | P20: =-P21*P13 -> -6580.5732 | Q20: =-Q21*Q13 -> -7111.5025 | R20: =-R21*R13 -> -7645.8653 | S20: =-S21*S13 -> -8178.0172 | T20: =-T21*T13 -> -8701.8949 | U20: =-U21*U13 -> -9211.1174 | V20: =-V21*V13 -> -9691.0166 | Y20: % of total revenue | Z20: 0.074007082 | AA20: 0.065121223 | AB20: 0.064179831 | AC20: 0.069711025 | AD20: 0.070471653 | AE20: 0.074254093 | AF20: 0.080663916 | AG20: 0.077573827 | AH20: 0.081264923 | AI20: 0.078337666 | AJ20: 0.050142651 | AK20: 0.06984839 | AL20: 0.0698 | AM20: 0.0698 | AN20: 0.0698 | AO20: 0.0698 | AP20: 0.0698 | AQ20: 0.0698 | AR20: 0.0698 | AS20: 0.0698 | AT20: 0.0698
A21: Net Income | B21: =-B20/B13 -> 0.39293362 | C21: =-C20/C13 -> 0.46683073 | D21: =-D20/D13 -> 0.44045977 | E21: =-E20/E13 -> 0.2468374 | F21: =-F20/F13 -> 0.23880397 | G21: =-G20/G13 -> 0.22057177 | H21: =-H20/H13 -> 0.25484268 | I21: =-I20/I13 -> 0.19098874 | ... L21: =-L20/L13 -> 0.20235561 | M21: =FS_Forecast!M21 -> 0.12632001 | N21: 0.1767 | O21: 0.1767 | P21: 0.1767 | Q21: 0.1767 | R21: 0.1767 | S21: 0.1767 | T21: 0.1767 | U21: 0.1767 | V21: 0.1767 | Y21: Provision for income taxes | Z21: -4037 | AA21: -4363 | AB21: -4790 | AC21: -3200 | AD21: -3562 | AE21: -3742 | AF21: -4973 | AG21: -4578 | AH21: -4829 | AI21: -5968 | AJ21: -5704 | AK21: -6315.2826 | AL21: -6190.1897 | AM21: -6275.5303 | AN21: -6569.1398 | AO21: -7093.268 | AP21: -7619.9177 | AQ21: -8143.4549 | AR21: -8657.8478 | AS21: -9156.7685 | AT21: -9633.8362
A22: Net Income | B22: =B18+B20 -> 5619 | C22: =C18+C20 -> 4193 | D22: =D18+D20 -> 5018 | E22: =E18+E20 -> 8578 | F22: =F18+F20 -> 9954 | G22: =G18+G20 -> 11519 | H22: =H18+H20 -> 12878 | I22: =I18+I20 -> 17732 | ... V22: =V18+V20 -> 38317.987 | Y22: Net Income | Z22: 0.39293362 | AA22: 0.39588059 | AB22: 0.3704563 | AC22: 0.21040174 | AD22: 0.20537362 | AE22: 0.19009398 | AF22: 0.22195938 | AG22: 0.19098874 | AH22: 0.16982592 | AI22: 0.18443662 | AJ22: 0.17666553 | AK22: 0.1767 | AL22: 0.1767 | AM22: 0.1767 | AN22: 0.1767 | AO22: 0.1767 | AP22: 0.1767 | AQ22: 0.1767 | AR22: 0.1767 | AS22: 0.1767 | AT22: 0.1767
B23: =B22/B4 -> 0.043066051 | C23: =C22/C4 -> 0.026688817 | D23: =D22/D4 -> 0.027147804 | E23: =E22/E4 -> 0.042642884 | F23: =F22/F4 -> 0.043996163 | G23: =G22/G4 -> 0.047568706 | H23: =H22/H4 -> 0.050081473 | I23: =I22/I4 -> 0.06165572 | ... L23: =L22/L4 -> 0.025652172 | M23: =FS_Forecast!M23 -> 0.0292068 | N23: =N22/N4 -> 0.05569934 | O23: =O22/O4 -> 0.055752737 | P23: =P22/P4 -> 0.055804447 | Q23: =Q22/Q4 -> 0.055854574 | R23: =R22/R4 -> 0.055904956 | S23: =S22/S4 -> 0.055955595 | T23: =T22/T4 -> 0.056006495 | U23: =U22/U4 -> 0.056057658 | V23: =V22/V4 -> 0.056057658 | Y23: Net Income | Z23: 5619 | AA23: 5868 | AB23: 7073 | AC23: 10823 | AD23: 12382 | AE23: 14239 | AF23: 15769 | AG23: 17732 | AH23: 21514 | AI23: 23144 | AJ23: 14367 | AK23: 24948.857 | AL23: 24452.01 | AM23: 24789.116 | AN23: 25948.91 | AO23: 28019.28 | AP23: 30099.611 | AQ23: 32167.648 | AR23: 34199.563 | AS23: 36170.361 | AT23: 38054.837
Z24: 0.043066051 | AA24: 0.037350341 | AB24: 0.038265527 | AC24: 0.05380321 | AD24: 0.054727797 | AE24: 0.058801181 | AF24: 0.061324332 | AG24: 0.06165572 | AH24: 0.066368051 | AI24: 0.062278337 | AJ24: 0.035892555 | AK24: 0.05573918 | AL24: 0.05569934 | AM24: 0.05569934 | AN24: 0.05569934 | AO24: 0.05569934 | AP24: 0.05569934 | AQ24: 0.05569934 | AR24: 0.05569934 | AS24: 0.05569934 | AT24: 0.05569934
B25: 1 | C25: 2 | D25: 3 | E25: 4 | F25: 5 | G25: 6 | H25: 7 | I25: 8 | J25: 9 | K25: 10 | L25: 11
A26: United Health Balance Sheet - 10K
B27: 2014 | C27: 2015 | D27: 2016 | E27: 2017 | F27: 2018 | G27: 2019 | H27: 2020 | I27: 2021 | J27: 2022 | K27: 2023 | L27: 2024 | M27: 2025(UA) | N27: 2026 | O27: 2027 | P27: 2028 | Q27: 2029 | R27: 2030 | S27: 2031 | T27: 2032
A28: Current assets:
A29: Cash and cash equivalents | B29: 7495 | C29: 10923 | D29: 10430 | E29: 11981 | F29: 10866 | G29: 10985 | H29: 16921 | I29: 21375 | J29: 23365 | K29: 25427 | L29: 25312 | M29: =FS_Forecast!M46 -> 24365
A31: Short-term investments | B31: 1741 | C31: 1988 | D31: 2845 | E31: 3509 | F31: 3458 | G31: 3260 | H31: 2860 | I31: 2532 | J31: 4546 | K31: 4201 | L31: 3801 | M31: 3801
A33: Accounts receivable, net | B33: 4252 | C33: 6523 | D33: 8152 | E33: 9568 | F33: 11388 | G33: 11822 | H33: 12870 | I33: 14216 | J33: 17681 | K33: 21276 | L33: 22365 | M33: 23018 | N33: =N34*FS_Forecast!N4 -> 22646.501 | O33: =O34*FS_Forecast!O4 -> 22958.715 | P33: =P34*FS_Forecast!P4 -> 23463.495 | Q33: =Q34*FS_Forecast!Q4 -> 24171.773 | R33: =R34*FS_Forecast!R4 -> 25099.641 | S33: =S34*FS_Forecast!S4 -> 26268.943 | T33: =T34*FS_Forecast!T4 -> 27713.735
A34: Account Receivables/Revenue | B34: =B33/B4 -> 0.032588868 | C34: =C33/C4 -> 0.041519474 | D34: =D33/D4 -> 0.044103008 | E34: =E33/E4 -> 0.047564365 | F34: =F33/F4 -> 0.050334369 | G34: =G33/G4 -> 0.048819971 | H34: =H33/H4 -> 0.050050361 | I34: =I33/I4 -> 0.049430279 | ... L34: =L33/L4 -> 0.055873668 | M34: =M33/FS_Forecast!M4 -> 0.051429172 | N34: =IFERROR(__xludf.DUMMYFUNCTION("AVERAGE.WEIGHTED(B34:M34,B1:M1)"),0.05158656170130325) -> 0.051586562 | O34: =N34 -> 0.051586562 | P34: =O34 -> 0.051586562 | Q34: =P34 -> 0.051586562 | R34: =Q34 -> 0.051586562 | S34: =R34 -> 0.051586562 | T34: =S34 -> 0.051586562
A35: Other current receivables, net | B35: 5498 | C35: 6801 | D35: 7499 | E35: 6262 | F35: 6862 | G35: 9640 | H35: 12534 | I35: 13866 | J35: 12769 | K35: 17694 | L35: 26089 | M35: 29697 | N35: =N36*FS_Forecast!N4 -> 29128.562 | O35: =O36*FS_Forecast!O4 -> 29530.14 | P35: =P36*FS_Forecast!P4 -> 30179.402 | Q35: =Q36*FS_Forecast!Q4 -> 31090.41 | R35: =R36*FS_Forecast!R4 -> 32283.86 | S35: =S36*FS_Forecast!S4 -> 33787.849 | T35: =T36*FS_Forecast!T4 -> 35646.181
A36: Other Receivables/Revenue | B36: =B35/B4 -> 0.042138664 | C36: =C35/C4 -> 0.043288969 | D36: =D35/D4 -> 0.040570223 | E36: =E35/E4 -> 0.031129604 | F36: =F35/F4 -> 0.030329684 | G36: =G35/G4 -> 0.039809213 | H36: =H35/H4 -> 0.048743685 | I36: =I35/I4 -> 0.048213298 | ... L36: =L35/L4 -> 0.065177202 | M36: =M35/FS_Forecast!M4 -> 0.066352077 | N36: =M36 -> 0.066352077 | O36: =N36 -> 0.066352077 | P36: =O36 -> 0.066352077 | Q36: =P36 -> 0.066352077 | R36: =Q36 -> 0.066352077 | S36: =R36 -> 0.066352077 | T36: =S36 -> 0.066352077
A37: Assets under management | B37: 2962 | C37: 2998 | D37: 3105 | E37: 3101 | F37: 3032 | G37: 3076 | H37: 4076 | I37: 4449 | J37: 4087 | K37: 3755 | L37: - | M37: - | N37: - | O37: - | P37: - | Q37: - | R37: - | S37: - | T37: -
A38: Deferred income taxes (current) | B38: 556 | C38: 860 | D38: - | E38: - | F38: - | G38: - | H38: - | I38: - | J38: - | K38: - | L38: - | M38: - | N38: - | O38: - | P38: - | Q38: - | R38: - | S38: - | T38: -
A39: Prepaid expenses and other current assets | B39: 1052 | C39: 1546 | D39: 1848 | E39: 2663 | F39: 3086 | G39: 3851 | H39: 4457 | I39: 5320 | J39: 6621 | K39: 6084 | L39: 8212 | M39: 9746 | N39: =N40*FS_Forecast!N4 -> 7756.4681 | O39: =O40*FS_Forecast!O4 -> 7863.402 | P39: =P40*FS_Forecast!P4 -> 8036.29 | Q39: =Q40*FS_Forecast!Q4 -> 8278.8768 | R39: =R40*FS_Forecast!R4 -> 8596.6732 | S39: =S40*FS_Forecast!S4 -> 8997.1614 | T39: =T40*FS_Forecast!T4 -> 9492.0053
A40: Prepaid Exp/Revenue | B40: =B39/B4 -> 0.0080629091 | C40: =C39/C4 -> 0.0098404272 | D40: =D39/D4 -> 0.009997836 | E40: =E39/E4 -> 0.013238284 | F40: =F39/F4 -> 0.01363996 | G40: =G39/G4 -> 0.015903037 | H40: =H39/H4 -> 0.017332903 | I40: =I39/I4 -> 0.018498107 | ... L40: =L39/L4 -> 0.020515742 | M40: =M39/FS_Forecast!M4 -> 0.021775511 | N40: =IFERROR(__xludf.DUMMYFUNCTION("AVERAGE.WEIGHTED(B40:M40,B1:M1)"),0.017668492154409552) -> 0.017668492 | O40: =N40 -> 0.017668492 | P40: =O40 -> 0.017668492 | Q40: =P40 -> 0.017668492 | R40: =Q40 -> 0.017668492 | S40: =R40 -> 0.017668492 | T40: =S40 -> 0.017668492
A41: Total current assets | B41: 23556 | C41: 31639 | D41: 33879 | E41: 37084 | F41: 38692 | G41: 42634 | H41: 53718 | I41: 61758 | J41: 69069 | K41: 78437 | L41: 85779 | M41: =SUM(M33+M35+M39) -> 62461 | N41: =SUM(N33+N35+N39) -> 59531.53 | O41: =SUM(O33+O35+O39) -> 60352.257 | P41: =SUM(P33+P35+P39) -> 61679.187 | Q41: =SUM(Q33+Q35+Q39) -> 63541.06 | R41: =SUM(R33+R35+R39) -> 65980.174 | S41: =SUM(S33+S35+S39) -> 69053.954 | T41: =SUM(T33+T35+T39) -> 72851.921
A42: Long-term investments | B42: 18827 | C42: 18792 | D42: 23868 | E42: 28341 | F42: 32510 | G42: 37209 | H42: 41242 | I42: 43114 | J42: 43728 | K42: 47609 | L42: 52354 | M42: 54251
A43: Property, equipment and capitalized software, net | B43: 4418 | C43: 4861 | D43: 5901 | E43: 7013 | F43: 8458 | G43: 8704 | H43: 8626 | I43: 8969 | J43: 10128 | K43: 11450 | L43: 10553 | M43: 10762 | N43: =N44*FS_Forecast!N4 -> 10556.002 | O43: =O44*FS_Forecast!O4 -> 10701.531 | P43: =P44*FS_Forecast!P4 -> 10936.819 | Q43: =Q44*FS_Forecast!Q4 -> 11266.963 | R43: =R44*FS_Forecast!R4 -> 11699.461 | S43: =S44*FS_Forecast!S4 -> 12244.497 | T43: =T44*FS_Forecast!T4 -> 12917.944
A44: PP&E/Revenue | B44: =B43/B4 -> 0.033861152 | C44: =C43/C4 -> 0.030940696 | D44: =D43/D4 -> 0.031924908 | E44: =E43/E4 -> 0.034862969 | F44: =F43/F4 -> 0.037383921 | G44: =G43/G4 -> 0.03594392 | H44: =H43/H4 -> 0.033545798 | I44: =I43/I4 -> 0.031186 | ... L44: =L43/L4 -> 0.026364177 | M44: =M43/FS_Forecast!M4 -> 0.024045562 | N44: =M44 -> 0.024045562 | O44: =N44 -> 0.024045562 | P44: =O44 -> 0.024045562 | Q44: =P44 -> 0.024045562 | R44: =Q44 -> 0.024045562 | S44: =R44 -> 0.024045562 | T44: =S44 -> 0.024045562
A45: Goodwill | B45: 32940 | C45: 44453 | D45: 47584 | E45: 54556 | F45: 58910 | G45: 65659 | H45: 71337 | I45: 75795 | J45: 93352 | K45: 103732 | L45: 106734 | M45: 110499 | N45: =M45*(1+N46) -> 140154.58 | O45: =N45*(1+O46) -> 142086.81 | P45: =O45*(1+P46) -> 145210.79 | Q45: =P45*(1+Q46) -> 149594.18 | R45: =Q45*(1+R46) -> 155336.56 | S45: =R45*(1+S46) -> 162573.14 | T45: =S45*(1+T46) -> 171514.66
A46: revenue growth | B46: =B45/B4 -> 0.25246409 | C46: =C45/C4 -> 0.28294729 | D46: =D45/D4 -> 0.25743346 | E46: =E45/E4 -> 0.27120835 | F46: =F45/F4 -> 0.26037914 | G46: =G45/G4 -> 0.27114451 | H46: =H45/H4 -> 0.27742367 | I46: =I45/I4 -> 0.26354586 | ... L46: =L45/L4 -> 0.26664968 | M46: =M45/FS_Forecast!M4 -> 0.24688818 | N46: =IFERROR(__xludf.DUMMYFUNCTION("AVERAGE.WEIGHTED(B46:M46,B1:M1)"),0.26837869991119045) -> 0.2683787 | O46: =FS_Forecast!O5 -> 0.013786416 | P46: =FS_Forecast!P5 -> 0.021986416 | Q46: =FS_Forecast!Q5 -> 0.030186416 | R46: =FS_Forecast!R5 -> 0.038386416 | S46: =FS_Forecast!S5 -> 0.046586416 | T46: =FS_Forecast!T5 -> 0.055
A47: Other intangible assets, net | B47: 3669 | C47: 8391 | D47: 8541 | E47: 8489 | F47: 9325 | G47: 10349 | H47: 10856 | I47: 10044 | J47: 14401 | K47: 15194 | L47: 23268 | M47: 20474 | N47: =N48*FS_Forecast!N4 -> 19568.341 | O47: =O48*FS_Forecast!O4 -> 19838.118 | P47: =P48*FS_Forecast!P4 -> 20274.287 | Q47: =Q48*FS_Forecast!Q4 -> 20886.295 | R47: =R48*FS_Forecast!R4 -> 21688.045 | S47: =S48*FS_Forecast!S4 -> 22698.414 | T47: =T48*FS_Forecast!T4 -> 23946.826
A48: Other Intangibles/Revenue | B48: =B47/B4 -> 0.028120545 | C48: =C47/C4 -> 0.05340946 | D48: =D47/D4 -> 0.046207531 | E48: =E47/E4 -> 0.042200448 | F48: =F47/F4 -> 0.041216016 | G48: =G47/G4 -> 0.04273709 | H48: =H47/H4 -> 0.042218083 | I48: =I47/I4 -> 0.034923869 | ... L48: =L47/L4 -> 0.0581296 | M48: =M47/FS_Forecast!M4 -> 0.045745106 | N48: =IFERROR(__xludf.DUMMYFUNCTION("AVERAGE.WEIGHTED(B48:M48,B1:M1)"),0.04457480836775548) -> 0.044574808 | O48: =N48 -> 0.044574808 | P48: =O48 -> 0.044574808 | Q48: =P48 -> 0.044574808 | R48: =Q48 -> 0.044574808 | S48: =R48 -> 0.044574808 | T48: =S48 -> 0.044574808
A49: Other assets | B49: 2972 | C49: 3247 | D49: 3037 | E49: 3575 | F49: 4326 | G49: 9334 | H49: 11510 | I49: 12526 | J49: 15027 | K49: 17298 | L49: 19590 | M49: 23013 | N49: =N50*FS_Forecast!N4 -> 18073.177 | O49: =O50*FS_Forecast!O4 -> 18322.341 | P49: =P50*FS_Forecast!P4 -> 18725.184 | Q49: =Q50*FS_Forecast!Q4 -> 19290.43 | R49: =R50*FS_Forecast!R4 -> 20030.92 | S49: =S50*FS_Forecast!S4 -> 20964.089 | T49: =T50*FS_Forecast!T4 -> 22117.114
A50: Other assets/revenue | B50: =B49/B4 -> 0.022778485 | C50: =C49/C4 -> 0.020667443 | D50: =D49/D4 -> 0.016430426 | E50: =E49/E4 -> 0.017772011 | F50: =F49/F4 -> 0.019120696 | G50: =G49/G4 -> 0.03854556 | H50: =H49/H4 -> 0.044761434 | I50: =I49/I4 -> 0.043554001 | ... M50: =M49/M4 -> 0.051418 | N50: =IFERROR(__xludf.DUMMYFUNCTION("AVERAGE.WEIGHTED(B50:M50,B1:M1)"),0.04116896753308679) -> 0.041168968 | O50: =N50 -> 0.041168968 | P50: =O50 -> 0.041168968 | Q50: =P50 -> 0.041168968 | R50: =Q50 -> 0.041168968 | S50: =R50 -> 0.041168968 | T50: =S50 -> 0.041168968
A51: Total Non Current Assets | B51: =SUM(B42,B43,B45,B47,B49) -> 62826 | C51: =SUM(C42,C43,C45,C47,C49) -> 79744 | D51: =SUM(D42,D43,D45,D47,D49) -> 88931 | E51: =SUM(E42,E43,E45,E47,E49) -> 101974 | F51: =SUM(F42,F43,F45,F47,F49) -> 113529 | G51: =SUM(G42,G43,G45,G47,G49) -> 131255 | H51: =SUM(H42,H43,H45,H47,H49) -> 143571 | I51: =SUM(I42,I43,I45,I47,I49) -> 150448 | ... T51: =SUM(T42,T43,T45,T47,T49) -> 230496.55
A52: Total assets | B52: 86382 | C52: 111383 | D52: 122810 | E52: 139058 | F52: 152221 | G52: 173889 | H52: 197289 | I52: 212206 | J52: 245705 | K52: 273720 | L52: 298278 | M52: =M51+M41 -> 281460 | N52: =N51+N41 -> 247883.63 | O52: =O51+O41 -> 251301.05 | P52: =P51+P41 -> 256826.26 | Q52: =Q51+Q41 -> 264578.93 | R52: =R51+R41 -> 274735.17 | S52: =S51+S41 -> 287534.09 | T52: =T51+T41 -> 303348.47
A54: Liabilities, redeemable noncontrolling interests and equity
A55: Current liabilities:
A56: Medical costs payable | B56: 14330 | C56: 14330 | D56: 16391 | E56: 17871 | F56: 19891 | G56: 21690 | H56: 21872 | I56: 24483 | J56: 29056 | K56: 32395 | L56: 34224 | M56: 39337 | N56: =N57*FS_Forecast!N7 -> 39059.714 | O56: =O57*FS_Forecast!O7 -> 39037.513 | P56: =P57*FS_Forecast!P7 -> 39895.808 | Q56: =Q57*FS_Forecast!Q7 -> 41100.12 | R56: =R57*FS_Forecast!R7 -> 42677.806 | S56: =S57*FS_Forecast!S7 -> 44666.012 | T56: =T57*FS_Forecast!T7 -> 47122.643
A57: Medical Costs/ COGS | B57: =B56/B7 -> 0.12070214 | C57: =C56/C7 -> 0.098104992 | D57: =D56/D7 -> 0.095346402 | E57: =E56/E7 -> 0.09610648 | F57: =F56/F7 -> 0.09521644 | G57: =G56/G7 -> 0.097496292 | H57: =H56/H7 -> 0.093177016 | I57: =I56/I7 -> 0.093975987 | ... L57: =L56/L7 -> 0.093002275 | M57: =M56/FS_Forecast!M7 -> 0.092723021 | N57: =IFERROR(__xludf.DUMMYFUNCTION("AVERAGE.WEIGHTED(B57:M57,B1:M1)"),0.09522207209327627) -> 0.095222072 | O57: =N57 -> 0.095222072 | P57: =O57 -> 0.095222072 | Q57: =P57 -> 0.095222072 | R57: =Q57 -> 0.095222072 | S57: =R57 -> 0.095222072 | T57: =S57 -> 0.095222072
A58: Accounts payable and accrued liabilities | B58: 11994 | C58: 11994 | D58: 13361 | E58: 15180 | F58: 16705 | G58: 19005 | H58: 22495 | I58: 24643 | J58: 27715 | K58: 31958 | L58: 34337 | M58: 38032 | N58: =N59*FS_Forecast!N7 -> 37145.912 | O58: =O59*FS_Forecast!O7 -> 37124.799 | P58: =P59*FS_Forecast!P7 -> 37941.04 | Q58: =Q59*FS_Forecast!Q7 -> 39086.344 | R58: =R59*FS_Forecast!R7 -> 40586.729 | S58: =S59*FS_Forecast!S7 -> 42477.519 | T58: =T59*FS_Forecast!T7 -> 44813.783
A59: Account Payable/COGS | B59: =B58/B7 -> 0.10102593 | C59: =C58/C7 -> 0.082112441 | D59: =D58/D7 -> 0.0777209 | E59: =E58/E7 -> 0.081634848 | F59: =F58/F7 -> 0.079965343 | G59: =G58/G7 -> 0.085427249 | H59: =H58/H7 -> 0.095831061 | I59: =I58/I7 -> 0.094590134 | ... L59: =L58/L7 -> 0.093309347 | M59: =M58/FS_Forecast!M7 -> 0.089646947 | N59: =IFERROR(__xludf.DUMMYFUNCTION("AVERAGE.WEIGHTED(B59:L59,B1:L1)"),0.09055649162470865) -> 0.090556492 | O59: =N59 -> 0.090556492 | P59: =O59 -> 0.090556492 | Q59: =P59 -> 0.090556492 | R59: =Q59 -> 0.090556492 | S59: =R59 -> 0.090556492 | T59: =S59 -> 0.090556492
A60: Short-term borrowings and current maturities of long-term debt | B60: 6634 | C60: 6634 | D60: 7193 | E60: 2857 | F60: 1973 | G60: 3870 | H60: 4819 | I60: 3620 | J60: 3110 | K60: 4274 | L60: 4545 | M60: 6069
A61: Unearned revenues | B61: 2142 | C61: 2142 | D61: 1968 | E61: 2269 | F61: 2396 | G61: 2622 | H61: 2842 | I61: 2571 | J61: 3075 | K61: 3355 | L61: 3317 | M61: 3413 | N61: =N62*FS_Forecast!N4 -> 3512 | O61: =O62*FS_Forecast!O4 -> 3560.4179 | P61: =P62*FS_Forecast!P4 -> 3638.6987 | Q61: =Q62*FS_Forecast!Q4 -> 3748.538 | R61: =R62*FS_Forecast!R4 -> 3892.4309 | S61: =S62*FS_Forecast!S4 -> 4073.7654 | T61: =T62*FS_Forecast!T4 -> 4297.8224
A62: Unearned revenue/revenue | B62: =B61/B4 -> 0.016417064 | C62: =C61/C4 -> 0.01363402 | D62: =D61/D4 -> 0.010647046 | E62: =E61/E4 -> 0.011279635 | F62: =F61/F4 -> 0.010590196 | G62: =G61/G4 -> 0.010827776 | H62: =H61/H4 -> 0.011052302 | I62: =I61/I4 -> 0.0089395926 | ... L62: =L61/L4 -> 0.0082867407 | M62: 0.008 | N62: 0.008 | O62: 0.008 | P62: 0.008 | Q62: 0.008 | R62: 0.008 | S62: 0.008 | T62: 0.008
A63: Other current liabilities | B63: 5965 | C63: 7798 | D63: 10339 | E63: 12286 | F63: 12244 | G63: 14595 | H63: 20392 | I63: 22975 | J63: 26281 | K63: 27072 | L63: 27346 | M63: 28046 | N63: =N64*FS_Forecast!N4 -> 30083.425 | O63: =O64*FS_Forecast!O4 -> 30498.168 | P63: =P64*FS_Forecast!P4 -> 31168.713 | Q63: =Q64*FS_Forecast!Q4 -> 32109.585 | R63: =R64*FS_Forecast!R4 -> 33342.157 | S63: =S64*FS_Forecast!S4 -> 34895.449 | T63: =T64*FS_Forecast!T4 -> 36814.698
A64: OCL/revenue | B64: =B63/B4 -> 0.045717921 | C64: =C63/C4 -> 0.049634962 | D64: =D63/D4 -> 0.055934863 | E64: =E63/E4 -> 0.061076064 | F64: =F63/F4 -> 0.054117845 | G64: =G63/G4 -> 0.060271314 | H64: =H63/H4 -> 0.079302795 | I64: =I63/I4 -> 0.079886091 | ... L64: =L63/L4 -> 0.068317519 | M64: =M63/FS_Forecast!M4 -> 0.062663244 | N64: =IFERROR(__xludf.DUMMYFUNCTION("AVERAGE.WEIGHTED(B64:M64,B1:M1)"),0.06852716456901024) -> 0.068527165 | O64: =N64 -> 0.068527165 | P64: =O64 -> 0.068527165 | Q64: =P64 -> 0.068527165 | R64: =Q64 -> 0.068527165 | S64: =R64 -> 0.068527165 | T64: =S64 -> 0.068527165
A65: Total current liabilities | B65: 16007 | C65: 25460 | D65: 49252 | E65: 50463 | F65: 53209 | G65: 61782 | H65: 72420 | I65: 78292 | J65: 89237 | K65: 99054 | L65: 103769 | M65: =SUM(M56,M58,M61,M63) -> 108828 | N65: =SUM(N56,N58,N61,N63) -> 109801.05 | O65: =SUM(O56,O58,O61,O63) -> 110220.9 | P65: =SUM(P56,P58,P61,P63) -> 112644.26 | Q65: =SUM(Q56,Q58,Q61,Q63) -> 116044.59 | R65: =SUM(R56,R58,R61,R63) -> 120499.12 | S65: =SUM(S56,S58,S61,S63) -> 126112.75 | T65: =SUM(T56,T58,T61,T63) -> 133048.95
A66: Long-term debt, less current maturities | B66: 2488 | C66: 2496 | D66: 25777 | E66: 28835 | F66: 34581 | G66: 36808 | H66: 38648 | I66: 42383 | J66: 54513 | K66: 58263 | L66: 72359 | M66: 72320
A67: Deferred income taxes | B67: 2065 | C67: 3587 | D67: 2761 | E67: 2182 | F67: 2474 | G67: 2993 | H67: 3367 | I67: 3265 | J67: 2769 | K67: 3021 | L67: 3620 | M67: =M68*FS_Forecast!M4 -> 4873.4282 | N67: =N68*FS_Forecast!N4 -> 4780.1446 | O67: =O68*FS_Forecast!O4 -> 4846.0457 | P67: =P68*FS_Forecast!P4 -> 4952.5929 | Q67: =Q68*FS_Forecast!Q4 -> 5102.0939 | R67: =R68*FS_Forecast!R4 -> 5297.945 | S67: =S68*FS_Forecast!S4 -> 5544.7573 | T67: =T68*FS_Forecast!T4 -> 5849.7189
A68: Deffered Tax/Revenue | B68: =B67/B4 -> 0.015826908 | C68: =C67/C4 -> 0.022831573 | D68: =D67/D4 -> 0.014937243 | E68: =E67/E4 -> 0.010847141 | F68: =F67/F4 -> 0.010934952 | G68: =G67/G4 -> 0.012359852 | H68: =H67/H4 -> 0.013093983 | I68: =I67/I4 -> 0.011352691 | ... L68: =L67/L4 -> 0.0090437146 | M68: =IFERROR(__xludf.DUMMYFUNCTION("AVERAGE.WEIGHTED(B68:L68,B1:L1)"),0.010888712169274183) -> 0.010888712 | N68: =M68 -> 0.010888712 | O68: =N68 -> 0.010888712 | P68: =O68 -> 0.010888712 | Q68: =P68 -> 0.010888712 | R68: =Q68 -> 0.010888712 | S68: =R68 -> 0.010888712 | T68: =S68 -> 0.010888712
A69: Other liabilities | B69: 1357 | C69: 1481 | D69: 4831 | E69: 5556 | F69: 5730 | G69: 10144 | H69: 12315 | I69: 11787 | J69: 12839 | K69: 14463 | L69: 15939 | M69: 18245 | N69: =N70*FS_Forecast!N4 -> 16502.342 | O69: =O70*FS_Forecast!O4 -> 16729.85 | P69: =P70*FS_Forecast!P4 -> 17097.679 | Q69: =Q70*FS_Forecast!Q4 -> 17613.797 | R69: =R70*FS_Forecast!R4 -> 18289.928 | S69: =S70*FS_Forecast!S4 -> 19141.99 | T69: =T70*FS_Forecast!T4 -> 20194.799
A70: OL/Revenues | B70: =B69/B4 -> 0.01040054 | C70: =C69/C4 -> 0.0094266965 | D70: =D69/D4 -> 0.026136118 | E70: =E69/E4 -> 0.027619942 | F70: =F69/F4 -> 0.025326303 | G70: =G69/G4 -> 0.041890525 | H70: =H69/H4 -> 0.047892013 | I70: =I69/I4 -> 0.040984433 | ... M70: =M69/M4 -> 0.040764846 | N70: =IFERROR(__xludf.DUMMYFUNCTION("AVERAGE.WEIGHTED(B70:M70,B1:M1)"),0.03759075573505806) -> 0.037590756 | O70: =N70 -> 0.037590756 | P70: =O70 -> 0.037590756 | Q70: =P70 -> 0.037590756 | R70: =Q70 -> 0.037590756 | S70: =R70 -> 0.037590756 | T70: =S70 -> 0.037590756
A71: Total non current liabilities | B71: 52540 | C71: 75922 | D71: 82621 | E71: 87036 | F71: 95994 | G71: 111727 | H71: 126750 | I71: 135727 | J71: 159358 | K71: 174801 | L71: 195687 | M71: 207883 | N71: =SUM(N66,N67,N69) -> 21282.486 | O71: =SUM(O66,O67,O69) -> 21575.896 | P71: =SUM(P66,P67,P69) -> 22050.272 | Q71: =SUM(Q66,Q67,Q69) -> 22715.891 | R71: =SUM(R66,R67,R69) -> 23587.873 | S71: =SUM(S66,S67,S69) -> 24686.747 | T71: =SUM(T66,T67,T69) -> 26044.518
A73: Redeemable noncontrolling interests | B73: 1388 | C73: 1736 | D73: 2012 | E73: 2189 | F73: 1908 | G73: 1726 | H73: 2211 | I73: 1434 | J73: 4897 | K73: 4498 | L73: 4323 | M73: 1608
A74: Equity:
A75: Common stock | B75: 10 | C75: 10 | D75: 10 | E75: 10 | F75: 10 | G75: 9 | H75: 10 | I75: 10 | J75: 9 | K75: 9 | L75: 9 | M75: 9
A76: Additional Paid In Capital | C76: 29 | E76: 1703
A77: Retained earnings | B77: 33836 | C77: 37125 | D77: 40945 | E77: 48730 | F77: 55846 | G77: 61178 | H77: 69295 | I77: 77134 | J77: 86156 | K77: 95774 | L77: 96036 | M77: 96036
A78: Accumulated other comprehensive loss | B78: -1392 | C78: -3334 | D78: -2681 | E78: -2667 | F78: -4160 | G78: -3578 | H78: -3814 | I78: -5384 | J78: -8393 | K78: -7027 | L78: -3387 | M78: -2061
A79: Nonredeemable noncontrolling interests | C79: -105 | D79: -97 | E79: 2057 | F79: 2623 | G79: 2820 | H79: 2837 | I79: 3285 | J79: 3678 | K79: 5665 | L79: 5610 | M79: 5910
A80: Total equity | B80: 32454 | C80: 33725 | D80: 38177 | E80: 49833 | F80: 54319 | G80: 60436 | H80: 68328 | I80: 75045 | J80: 81450 | K80: 94421 | L80: 98268 | M80: 100090
A81: Total liabilities, redeemable noncontrolling interests and equity | B81: 86382 | C81: 111383 | D81: 122810 | E81: 139058 | F81: 152221 | G81: 173889 | H81: 197289 | I81: 212206 | J81: 245705 | K81: 273720 | L81: 298278 | M81: 309581
H82: \
B299: 2016 | C299: 2017 | D299: 2018 | H299: 2014 | I299: 2015
A300: Revenues:
A301: Premiums | B301: 144118 | C301: 158453 | D301: 178087 | H301: 115302 | I301: 127163
A302: Products | B302: 26658 | C302: 26366 | D302: 29601 | H302: 4242 | I302: 17312
A303: Services | B303: 13236 | C303: 15317 | D303: 17183 | E303: =SUM(B301:B303) -> 184012 | F303: =SUM(C301:C303) -> 200136 | G303: =SUM(D301:D303) -> 224871 | H303: 10151 | I303: 11922 | J303: =SUM(H301:H303) -> 129695 | K303: =SUM(I301:I303) -> 156397
A304: Investment and other income | B304: 828 | C304: 1023 | D304: 1376 | H304: 779 | I304: 710
A305: Total revenues | B305: 184840 | C305: 201159 | D305: 226247 | H305: 130474 | I305: 157107
A307: Operating costs:
A308: Medical costs | B308: 117038 | C308: 130036 | D308: 145403 | H308: 93633 | I308: 103875
A309: Operating costs | B309: 28401 | C309: 29557 | D309: 34074 | H309: 21263 | I309: 24312
A310: Cost of products sold | B310: 24416 | C310: 24112 | D310: 26998 | H310: 3826 | I310: 16206
A311: Depreciation and amortization | B311: 2055 | C311: 2245 | D311: 2428 | H311: 1478 | I311: 1693
A312: Total operating costs | B312: 171910 | C312: 185950 | D312: 208903 | H312: 120200 | I312: 146086
A314: Earnings from operations | B314: 12930 | C314: 15209 | D314: 17344 | H314: 10274 | I314: 11021
A315: Interest expense | B315: -1067 | C315: -1186 | D315: -1400 | H315: -618 | I315: -790
A316: Earnings before income taxes | B316: 11863 | C316: 14023 | D316: 15944 | H316: 9656 | I316: 10231
A317: Provision for income taxes | B317: -4790 | C317: -3200 | D317: -3562 | H317: -4037 | I317: -4363
A318: Net earnings | B318: 7073 | C318: 10823 | D318: 12382 | H318: 5619 | I318: 5868
A319: Earnings attributable to noncontrolling interests | B319: -56 | C319: -265 | D319: -396 | H319: 0 | I319: -55
A320: Net earnings attributable to UNH common shareholders | B320: 7017 | C320: 10558 | D320: 11986 | H320: 5619 | I320: 5813
... A326: Diluted weighted-average shares outstanding (millions) | B326: 968 | C326: 985 | D326: 983 | H326: 986 | I326: 967
B327: 3 | C327: 5 | D327: 6 | H327: 6 | I327: 8
...

Sheet FS_Forecast
B1: 1 | C1: 2 | D1: 3 | E1: 4 | F1: 5 | G1: 6 | H1: 7 | I1: 8 | J1: 9 | K1: 10 | L1: 11 | M1: 12 | N1: 13
B2: United Health Income Statement - Actuals | N2: Forecasts
B3: 2014 | C3: 2015 | D3: 2016 | E3: 2017 | F3: 2018 | G3: 2019 | H3: 2020 | I3: 2021 | J3: 2022 | K3: 2023 | L3: 2024 | M3: 2025(UA) | N3: 2026 | O3: 2027 | P3: 2028 | Q3: 2029 | R3: 2030 | S3: 2031 | T3: 2032
A4: Total revenues | B4: 130474 | C4: 157107 | D4: 184840 | E4: 201159 | F4: 226247 | G4: 242155 | H4: 257141 | I4: 287597 | J4: 324162 | K4: 371622 | L4: 400278 | M4: 447567 | N4: 439000 | O4: =N4*(1+O5) -> 445052.24 | P4: =O4*(1+P5) -> 454837.34 | Q4: =P4*(1+Q5) -> 468567.25 | R4: =Q4*(1+R5) -> 486553.87 | S4: =R4*(1+S5) -> 509220.67 | T4: =S4*(1+T5) -> 537227.81
A5: % increase in revenue | B5: -% | C5: 0.20412496 | D5: 0.17652301 | E5: 0.088287167 | F5: 0.12471726 | G5: 0.070312535 | H5: 0.061885982 | I5: 0.11844086 | J5: 0.12713971 | K5: 0.14640828 | L5: 0.077110612 | M5: 0.11822284 | N5: -0.019213584 | O5: 0.013786416 | P5: =O5+0.82% -> 0.021986416 | Q5: =P5+0.82% -> 0.030186416 | R5: =Q5+0.82% -> 0.038386416 | S5: =R5+0.82% -> 0.046586416 | T5: 0.055
D6: 1 | E6: 2 | F6: 3 | I6: 4 | J6: 5 | K6: 6 | L6: 7 | R6: 0.00554
A7: Total Cost Of Goods Sold | B7: 118722 | C7: 146068 | D7: 171910 | E7: 185950 | F7: 208903 | G7: 222470 | H7: 234736 | I7: 260524 | J7: 295727 | K7: 339264 | L7: 367991 | M7: =313995+59592+50655 -> 424242 | N7: =N4-N9 -> 410196.01 | O7: =O4*O8 -> 409962.86 | P7: =P4*P8 -> 418976.48 | Q7: =Q4*Q8 -> 431623.88 | R7: =R4*R8 -> 448192.37 | S7: =S4*S8 -> 469072.05 | T7: =T4*T8 -> 494871.01
A8: % of total revenue | B8: =B7/B4 -> 0.90992841 | C8: =C7/C4 -> 0.92973579 | D8: =D7/D4 -> 0.93004761 | E8: =E7/E4 -> 0.92439314 | F8: =F7/F4 -> 0.92334042 | G8: =G7/G4 -> 0.91870909 | H8: =H7/H4 -> 0.91286882 | I8: =I7/I4 -> 0.9058648 | ... M8: =M7/M4 -> 0.9478849 | N8: =IFERROR(__xludf.DUMMYFUNCTION("AVERAGE.WEIGHTED(B8:M8,B1:M1)"),0.921156733808051) -> 0.92115673 | O8: =IFERROR(__xludf.DUMMYFUNCTION("AVERAGE.WEIGHTED(B8:N8,B1:N1)"),0.921156733808051) -> 0.92115673 | P8: =O8 -> 0.92115673 | Q8: =P8 -> 0.92115673 | R8: =Q8 -> 0.92115673 | S8: =R8 -> 0.92115673 | T8: =S8 -> 0.92115673
A9: Gross Profit | B9: 11752 | C9: 12714 | D9: 14985 | E9: 17454 | F9: 19772 | G9: 22405 | H9: 25296 | I9: 27073 | J9: 31835 | K9: 36330 | L9: 36386 | M9: =M4-M7 -> 23325 | N9: =N13+N11 -> 28803.987 | O9: =O4-O7 -> 35089.372 | P9: =P4-P7 -> 35860.862 | Q9: =Q4-Q7 -> 36943.372 | R9: =R4-R7 -> 38361.496 | S9: =S4-S7 -> 40148.621 | T9: =T4-T7 -> 42356.795
A10: % of total revenue | B10: 0.090071585 | C10: 0.080925739 | D10: 0.081070115 | E10: 0.086767184 | F10: 0.087391214 | G10: 0.092523384 | H10: 0.098374044 | I10: 0.094135196 | J10: 0.098207069 | K10: 0.097760628 | L10: 0.090901823 | M10: =M9/M4 -> 0.052115102 | N10: =N9/N4 -> 0.065612726 | O10: =O9/O4 -> 0.078843266 | P10: =P9/P4 -> 0.078843266 | Q10: =Q9/Q4 -> 0.078843266 | R10: =R9/R4 -> 0.078843266 | S10: =S9/S4 -> 0.078843266 | T10: =T9/T4 -> 0.078843266
A11: Depreciation and amortization | B11: 1478 | C11: 1693 | D11: 2055 | E11: 2245 | F11: 2428 | G11: 2720 | H11: 2891 | I11: 3103 | J11: 3400 | K11: 3972 | L11: 4099 | M11: =M9-M13 -> 4361 | N11: =N12*N4 -> 4658.9867 | O11: =O12*O4 -> 4723.2174 | P11: =P12*P4 -> 4827.064 | Q11: =Q12*Q4 -> 4972.7758 | R11: =R12*R4 -> 5163.6628 | S11: =S12*S4 -> 5404.2194 | T11: =T12*T4 -> 5701.4514
A12: % of total revenue | B12: 0.011327927 | C12: 0.010776095 | D12: 0.011117723 | E12: 0.011160326 | F12: 0.010731634 | G12: 0.011232475 | H12: 0.011242859 | I12: 0.010789403 | J12: 0.010488583 | K12: 0.01068828 | L12: 0.010240383 | M12: =M11/M4 -> 0.0097437925 | N12: =IFERROR(__xludf.DUMMYFUNCTION("AVERAGE.WEIGHTED(B12:M12,B1:M1)"),0.010612725897022154) -> 0.010612726 | O12: =N12 -> 0.010612726 | P12: =O12 -> 0.010612726 | Q12: =P12 -> 0.010612726 | R12: =Q12 -> 0.010612726 | S12: =R12 -> 0.010612726 | T12: =S12 -> 0.010612726
A13: EBIT | B13: 10274 | C13: 11021 | D13: 12930 | E13: 15209 | F13: 17344 | G13: 19685 | H13: 22405 | I13: 23970 | J13: 28435 | K13: 32358 | L13: 32287 | M13: 18964 | N13: =N4*N14 -> 24145 | O13: =O9-O11 -> 30366.155 | P13: =P9-P11 -> 31033.798 | Q13: =Q9-Q11 -> 31970.597 | R13: =R9-R11 -> 33197.833 | S13: =S9-S11 -> 34744.401 | T13: =T9-T11 -> 36655.343
A14: % of total revenue | B14: 0.078743658 | C14: 0.070149643 | D14: 0.069952391 | E14: 0.075606858 | F14: 0.07665958 | G14: 0.081290909 | H14: 0.087131185 | I14: 0.083345793 | J14: 0.087718486 | K14: 0.087072348 | L14: 0.08066144 | M14: =M13/M4 -> 0.04237131 | N14: 0.055 | O14: =O13/O4 -> 0.06823054 | P14: =P13/P4 -> 0.06823054 | Q14: =Q13/Q4 -> 0.06823054 | R14: =R13/R4 -> 0.06823054 | S14: =S13/S4 -> 0.06823054 | T14: =T13/T4 -> 0.06823054
A15: Interest expense | B15: -618 | C15: -790 | D15: -1067 | E15: -1186 | F15: -1400 | G15: -1704 | H15: -1663 | I15: -1660 | J15: -2092 | K15: -3246 | L15: -3906 | M15: -4002 | N15: =-N16*N4 -> -3266.447 | O15: =-O16*O4 -> -3311.4796 | P15: =-P16*P4 -> -3384.2872 | Q15: =-Q16*Q4 -> -3486.4467 | R15: =-R16*R4 -> -3620.2789 | S15: =-S16*S4 -> -3788.9347 | T15: =-T16*T4 -> -3997.3261
A16: % of total revenue | B16: 0.0047365759 | C16: 0.0050284201 | D16: 0.0057725601 | E16: 0.0058958336 | F16: 0.0061879274 | G16: 0.0070368153 | H16: 0.0064672689 | I16: 0.0057719656 | J16: 0.0064535633 | K16: 0.008734682 | L16: 0.009758218 | M16: =-M15/M4 -> 0.008941678 | N16: =IFERROR(__xludf.DUMMYFUNCTION("AVERAGE.WEIGHTED(B16:M16,B1:M1)"),0.007440653737003448) -> 0.0074406537 | O16: =N16 -> 0.0074406537 | P16: =O16 -> 0.0074406537 | Q16: =P16 -> 0.0074406537 | R16: =Q16 -> 0.0074406537 | S16: =R16 -> 0.0074406537 | T16: =S16 -> 0.0074406537
A17: Loss on sale of subsidiary and subsidiaries held for sale | B17: 0 | C17: 0 | D17: 0 | E17: 0 | F17: 0 | G17: 0 | H17: 0 | I17: 0 | J17: 0 | K17: 0 | L17: -8310 | M17: 0 | N17: 0 | O17: 0 | P17: 0 | Q17: 0 | R17: 0 | S17: 0 | T17: 0
A18: Earnings Before Tax | B18: 9656 | C18: 10231 | D18: 11863 | E18: 14023 | F18: 15944 | G18: 17981 | H18: 20742 | I18: 22310 | J18: 26343 | K18: =K13+K15 -> 29112 | L18: 20071 | M18: =M13+M15 -> 14962 | N18: =N13+N15 -> 20878.553 | O18: =O13+O15 -> 27054.675 | P18: =P13+P15 -> 27649.51 | Q18: =Q13+Q15 -> 28484.15 | R18: =R13+R15 -> 29577.554 | S18: =S13+S15 -> 30955.467 | T18: =T13+T15 -> 32658.017
A19: % of total revenue | B19: 0.074007082 | C19: 0.065121223 | D19: 0.064179831 | E19: 0.069711025 | F19: 0.070471653 | G19: 0.074254093 | H19: 0.080663916 | I19: 0.077573827 | J19: 0.081264923 | K19: 0.078337666 | L19: 0.050142651 | M19: =M18/M4 -> 0.033429632 | N19: =N18/N4 -> 0.047559346 | O19: =O18/O4 -> 0.060789887 | P19: =P18/P4 -> 0.060789887 | Q19: =Q18/Q4 -> 0.060789887 | R19: =R18/R4 -> 0.060789887 | S19: =S18/S4 -> 0.060789887 | T19: =T18/T4 -> 0.060789887
A20: Provision for income taxes | B20: -4037 | C20: -4363 | D20: -4790 | E20: -3200 | F20: -3562 | G20: -3742 | H20: -4973 | I20: -4578 | J20: -4829 | K20: -5968 | L20: -4829 | M20: =-1890 -> -1890 | N20: =-N18*N21 -> -4880.2173 | O20: =-O18*O21 -> -6323.8431 | P20: =-P18*P21 -> -6462.8818 | Q20: =-Q18*Q21 -> -6657.973 | R20: =-R18*R21 -> -6913.5487 | S20: =-S18*S21 -> -7235.6262 | T20: =-T18*T21 -> -7633.5856
A21: tax rate | B21: =-B20/B18 -> 0.41808202 | C21: =-C20/C18 -> 0.42644903 | D21: =-D20/D18 -> 0.40377645 | E21: =-E20/E18 -> 0.22819653 | F21: =-F20/F18 -> 0.22340692 | G21: =-G20/G18 -> 0.20810856 | H21: =-H20/H18 -> 0.23975509 | I21: =-I20/I18 -> 0.20519946 | ... M21: =-M20/M18 -> 0.12632001 | N21: =IFERROR(__xludf.DUMMYFUNCTION("AVERAGE.WEIGHTED(B21:L21,B1:L1)"),0.23374308179355377) -> 0.23374308 | O21: =N21 -> 0.23374308 | P21: =O21 -> 0.23374308 | Q21: =P21 -> 0.23374308 | R21: =Q21 -> 0.23374308 | S21: =R21 -> 0.23374308 | T21: =S21 -> 0.23374308
A22: Net Income | B22: 5619 | C22: 5868 | D22: 7073 | E22: 10823 | F22: 12382 | G22: 14239 | H22: 15769 | I22: 17732 | J22: 21514 | K22: =K18*(1-K21) -> 23144 | L22: =L18*(1-L21) -> 15242 | M22: =M18*(1-M21) -> 13072 | N22: =N18*(1-N21) -> 15998.336 | O22: =O18+O20 -> 20730.832 | P22: =P18+P20 -> 21186.629 | Q22: =Q18+Q20 -> 21826.177 | R22: =R18+R20 -> 22664.006 | S22: =S18+S20 -> 23719.84 | T22: =T18+T20 -> 25024.432
B23: 0.043066051 | C23: 0.037350341 | D23: 0.038265527 | E23: 0.05380321 | F23: 0.054727797 | G23: 0.058801181 | H23: 0.061324332 | I23: 0.06165572 | J23: 0.066368051 | K23: 0.062278337 | L23: 0.035892555 | M23: =M22/M4 -> 0.0292068 | N23: =N22/N4 -> 0.036442678 | O23: =O22/O4 -> 0.046580671 | P23: =P22/P4 -> 0.046580671 | Q23: =Q22/Q4 -> 0.046580671 | R23: =R22/R4 -> 0.046580671 | S23: =S22/S4 -> 0.046580671 | T23: =T22/T4 -> 0.046580671
B27: Calculation Of Operating working Capital
B28: 2014 | C28: 2015 | D28: 2016 | E28: 2017 | F28: 2018 | G28: 2019 | H28: 2020 | I28: 2021 | J28: 2022 | K28: 2023 | L28: 2024 | M28: 2025 | N28: 2026 | O28: 2027 | P28: 2028 | Q28: 2029 | R28: 2030 | S28: 2031 | T28: 2032
A29: Operating Assets
A30: Accounts receivable, net | B30: =Financials!B33 -> 4252 | C30: =Financials!C33 -> 6523 | D30: =Financials!D33 -> 8152 | E30: =Financials!E33 -> 9568 | F30: =Financials!F33 -> 11388 | G30: =Financials!G33 -> 11822 | H30: =Financials!H33 -> 12870 | I30: =Financials!I33 -> 14216 | ... T30: =Financials!T33 -> 27713.735
A31: Other current receivables, net | B31: =Financials!B35 -> 5498 | C31: =Financials!C35 -> 6801 | D31: =Financials!D35 -> 7499 | E31: =Financials!E35 -> 6262 | F31: =Financials!F35 -> 6862 | G31: =Financials!G35 -> 9640 | H31: =Financials!H35 -> 12534 | I31: =Financials!I35 -> 13866 | ... T31: =Financials!T35 -> 35646.181
A32: Prepaid expenses and other current assets | B32: =Financials!B39 -> 1052 | C32: =Financials!C39 -> 1546 | D32: =Financials!D39 -> 1848 | E32: =Financials!E39 -> 2663 | F32: =Financials!F39 -> 3086 | G32: =Financials!G39 -> 3851 | H32: =Financials!H39 -> 4457 | I32: =Financials!I39 -> 5320 | ... T32: =Financials!T39 -> 9492.0053
A33: Total operating Assets | B33: =SUM(B30:B32) -> 10802 | C33: =SUM(C30:C32) -> 14870 | D33: =SUM(D30:D32) -> 17499 | E33: =SUM(E30:E32) -> 18493 | F33: =SUM(F30:F32) -> 21336 | G33: =SUM(G30:G32) -> 25313 | H33: =SUM(H30:H32) -> 29861 | I33: =SUM(I30:I32) -> 33402 | ... T33: =SUM(T30:T32) -> 72851.921
A34: Operating Liabilities
A35: =Financials!A56 -> Medical costs payable | B35: =Financials!B56 -> 14330 | C35: =Financials!C56 -> 14330 | D35: =Financials!D56 -> 16391 | E35: =Financials!E56 -> 17871 | F35: =Financials!F56 -> 19891 | G35: =Financials!G56 -> 21690 | H35: =Financials!H56 -> 21872 | ... T35: =Financials!T56 -> 47122.643
A36: =Financials!A58 -> Accounts payable and accrued liabilities | B36: =Financials!B58 -> 11994 | C36: =Financials!C58 -> 11994 | D36: =Financials!D58 -> 13361 | E36: =Financials!E58 -> 15180 | F36: =Financials!F58 -> 16705 | G36: =Financials!G58 -> 19005 | H36: =Financials!H58 -> 22495 | ... T36: =Financials!T58 -> 44813.783
A37: =Financials!A63 -> Other current liabilities | B37: 5965 | C37: 7798 | D37: =Financials!D63 -> 10339 | E37: =Financials!E63 -> 12286 | F37: =Financials!F63 -> 12244 | G37: =Financials!G63 -> 14595 | H37: =Financials!H63 -> 20392 | I37: =Financials!I63 -> 22975 | J37: =Financials!J63 -> 26281 | K37: =Financials!K63 -> 27072 | ... T37: =Financials!T63 -> 36814.698
A38: =Financials!A61 -> Unearned revenues | B38: =Financials!B61 -> 2142 | C38: =Financials!C61 -> 2142 | D38: =Financials!D61 -> 1968 | E38: =Financials!E61 -> 2269 | F38: =Financials!F61 -> 2396 | G38: =Financials!G61 -> 2622 | H38: =Financials!H61 -> 2842 | ... T38: =Financials!T61 -> 4297.8224
A39: Total Operating Liabilities | B39: =SUM(B35:B38) -> 34431 | C39: =SUM(C35:C38) -> 36264 | D39: =SUM(D35:D38) -> 42059 | E39: =SUM(E35:E38) -> 47606 | F39: =SUM(F35:F38) -> 51236 | G39: =SUM(G35:G38) -> 57912 | H39: =SUM(H35:H38) -> 67601 | I39: =SUM(I35:I38) -> 74672 | ... T39: =SUM(T35:T38) -> 133048.95
A40: Working Capital | B40: =B33-B39 -> -23629 | C40: =C33-C39 -> -21394 | D40: =D33-D39 -> -24560 | E40: =E33-E39 -> -29113 | F40: =F33-F39 -> -29900 | G40: =G33-G39 -> -32599 | H40: =H33-H39 -> -37740 | I40: =I33-I39 -> -41270 | ... T40: =T33-T39 -> -60197.025
A41: Change in NWC | C41: =C40-B40 -> 2235 | D41: =D40-C40 -> -3166 | E41: =E40-D40 -> -4553 | F41: =F40-E40 -> -787 | G41: =G40-F40 -> -2699 | H41: =H40-G40 -> -5141 | I41: =I40-H40 -> -3530 | J41: =J40-I40 -> -7786 | ... T41: =T40-S40 -> -3138.2335
A42: NWC/Revenue
B45: 2014 | C45: 2015 | D45: 2016 | E45: 2017 | F45: 2018 | G45: 2019 | H45: 2020 | I45: 2021 | J45: 2022 | K45: 2023 | L45: 2024 | M45: 2025
A46: Cash | B46: =Financials!B29 -> 7495 | C46: =Financials!C29 -> 10923 | D46: =Financials!D29 -> 10430 | E46: =Financials!E29 -> 11981 | F46: =Financials!F29 -> 10866 | G46: =Financials!G29 -> 10985 | H46: =Financials!H29 -> 16921 | I46: =Financials!I29 -> 21375 | ... L46: =Financials!L29 -> 25312 | M46: 24365
A47: Non Cash Net Working Capital | B47: =B40 -> -23629 | C47: =C40 -> -21394 | D47: =D40 -> -24560 | E47: =E40 -> -29113 | F47: =F40 -> -29900 | G47: =G40 -> -32599 | H47: =H40 -> -37740 | I47: =I40 -> -41270 | ... M47: =M40 -> -46367
A48: Net Fixed Assets | B48: =Financials!B45+Financials!B43+Financials!B47+Financials!B49 -> 43999 | C48: =Financials!C45+Financials!C43+Financials!C47+Financials!C49 -> 60952 | D48: =Financials!D45+Financials!D43+Financials!D47+Financials!D49 -> 65063 | E48: =Financials!E45+Financials!E43+Financials!E47+Financials!E49 -> 73633 | F48: =Financials!F45+Financials!F43+Financials!F47+Financials!F49 -> 81019 | G48: =Financials!G45+Financials!G43+Financials!G47+Financials!G49 -> 94046 | H48: =Financials!H45+Financials!H43+Financials!H47+Financials!H49 -> 102329 | I48: =Financials!I45+Financials!I43+Financials!I47+Financials!I49 -> 107334 | ... M48: =Financials!M45+Financials!M43+Financials!M47+Financials!M49 -> 164748
A49: Invested Capital | B49: =B46+B47+B48 -> 27865 | C49: =C46+C47+C48 -> 50481 | D49: =D46+D47+D48 -> 50933 | E49: =E46+E47+E48 -> 56501 | F49: =F46+F47+F48 -> 61985 | G49: =G46+G47+G48 -> 72432 | H49: =H46+H47+H48 -> 81510 | I49: =I46+I47+I48 -> 87439 | ... M49: =M46+M47+M48 -> 142746
A50: ROIC | B50: =B22/B49 -> 0.20165082 | C50: =C22/C49 -> 0.11624175 | D50: =D22/D49 -> 0.13886871 | E50: =E22/E49 -> 0.19155413 | F50: =F22/F49 -> 0.19975801 | G50: =G22/G49 -> 0.19658438 | H50: =H22/H49 -> 0.19346093 | I50: =I22/I49 -> 0.2027928 | ... M50: =M22/M49 -> 0.091575246
A56: 1. The net profit margin for 2025 is expected to be 2.70% as per the earnings report.
A57: 2. The operating income for 2025 was 19 Million, Adjusted for one time, non - recurring items for 2.24 Mn
A58: 3. the company discontinued the AUM disclosure.
A59: 4. Other Operating Liab include: Health Savings Account (HSA) deposits,Premium rebates payable Current portion of future policy benefits and Customer balances
A60: 5. The jump in 2024 is explained by Temporary loans due to the Change Healthcare cyberattack
A61: 6. Management actually expects improvement in costs
A62: 7. The effective income tax rate decreased due to tax benefits having significantly more impact due to lower pre-tax income in 2025, impacts of net portfolio divestitures, and due to non-deductible losses on the sale of subsidiary and subsidiaries held for sale in 2024.
A63: 8. The current and long-term portions of CDs are included within other current liabilities
B77: =#REF!/$B$4 -> #REF! | C77: =#REF!/$C$4 -> #REF! | D77: =#REF!/$D$4 -> #REF! | E77: =#REF!/$E$4 -> #REF! | F77: =#REF!/$F$4 -> #REF! | G77: =#REF!/$G$4 -> #REF! | H77: =#REF!/$H$4 -> #REF! | I77: =#REF!/$I$4 -> #REF! | J77: =#REF!/$J$4 -> #REF! | K77: =#REF!/$K$4 -> #REF! | L77: =#REF!/$L$4 -> #REF! | M77: =IFERROR(__xludf.DUMMYFUNCTION("AVERAGE.WEIGHTED(B77:L77,B96:L96)"),"#REF!") -> #REF! | N77: =M77 -> #REF! | O77: =N77 -> #REF! | P77: =O77 -> #REF! | Q77: =P77 -> #REF! | R77: =Q77 -> #REF! | S77: =R77 -> #REF! | T77: =S77 -> #REF! | U77: =T77 -> #REF! | V77: =U77 -> #REF!
B78: =B30/$B$4 -> 0.032588868 | C78: =C30/$C$4 -> 0.041519474 | D78: =D30/$D$4 -> 0.044103008 | E78: =E30/$E$4 -> 0.047564365 | F78: =F30/$F$4 -> 0.050334369 | G78: =G30/$G$4 -> 0.048819971 | H78: =H30/$H$4 -> 0.050050361 | I78: =I30/$I$4 -> 0.049430279 | J78: =J30/$J$4 -> 0.054543716 | K78: =K30/$K$4 -> 0.057251724 | L78: =L30/$L$4 -> 0.055873668 | M78: =IFERROR(__xludf.DUMMYFUNCTION("AVERAGE.WEIGHTED(B78:L78,B96:L96)"),0.05161517810184102) -> 0.051615178 | N78: =M78 -> 0.051615178 | O78: =N78 -> 0.051615178 | P78: =O78 -> 0.051615178 | Q78: =P78 -> 0.051615178 | R78: =Q78 -> 0.051615178 | S78: =R78 -> 0.051615178 | T78: =S78 -> 0.051615178 | U78: =T78 -> 0.051615178 | V78: =U78 -> 0.051615178
B79: =B31/$B$4 -> 0.042138664 | C79: =C31/$C$4 -> 0.043288969 | D79: =D31/$D$4 -> 0.040570223 | E79: =E31/$E$4 -> 0.031129604 | F79: =F31/$F$4 -> 0.030329684 | G79: =G31/$G$4 -> 0.039809213 | H79: =H31/$H$4 -> 0.048743685 | I79: =I31/$I$4 -> 0.048213298 | J79: =J31/$J$4 -> 0.039390798 | K79: =K31/$K$4 -> 0.047612897 | L79: =L31/$L$4 -> 0.065177202 | M79: =IFERROR(__xludf.DUMMYFUNCTION("AVERAGE.WEIGHTED(B79:L79,B96:L96)"),0.04605995371193669) -> 0.046059954 | N79: =M79 -> 0.046059954 | O79: =N79 -> 0.046059954 | P79: =O79 -> 0.046059954 | Q79: =P79 -> 0.046059954 | R79: =Q79 -> 0.046059954 | S79: =R79 -> 0.046059954 | T79: =S79 -> 0.046059954 | U79: =T79 -> 0.046059954 | V79: =U79 -> 0.046059954
B80: =B32/$B$4 -> 0.0080629091 | C80: =C32/$C$4 -> 0.0098404272 | D80: =D32/$D$4 -> 0.009997836 | E80: =E32/$E$4 -> 0.013238284 | F80: =F32/$F$4 -> 0.01363996 | G80: =G32/$G$4 -> 0.015903037 | H80: =H32/$H$4 -> 0.017332903 | I80: =I32/$I$4 -> 0.018498107 | J80: =J32/$J$4 -> 0.020424973 | K80: =K32/$K$4 -> 0.016371474 | L80: =L32/$L$4 -> 0.020515742
M83: =M33-M39 -> -46367 | N83: =N33-N39 -> -50269.521 | O83: =O33-O39 -> -49868.641 | P83: =P33-P39 -> -50965.074 | Q83: =Q33-Q39 -> -52503.527 | R83: =R33-R39 -> -54518.949 | S83: =S33-S39 -> -57058.791 | T83: =T33-T39 -> -60197.025 | ... V83: =V33-V39 -> 0
M84: =M83-L40 -> -3809 | N84: =N83-M40 -> -3902.521 | O84: =O83-N40 -> 400.87994 | P84: =P83-O40 -> -1096.4327 | Q84: =Q83-P40 -> -1538.4529 | R84: =R83-Q40 -> -2015.4222 | S84: =S83-R40 -> -2539.8425 | T84: =T83-S40 -> -3138.2335 | ... V84: =V83-U40 -> 0
B96: 1 | C96: 2 | D96: 3 | E96: 4 | F96: 5 | G96: 6 | H96: 7 | I96: 8 | J96: 9 | K96: 10 | L96: 11
M98: =M77*M4 -> #REF! | N98: =N77*N4 -> #REF! | O98: =O77*O4 -> #REF! | P98: =P77*P4 -> #REF! | Q98: =Q77*Q4 -> #REF! | R98: =R77*R4 -> #REF! | S98: =S77*S4 -> #REF! | T98: =T77*T4 -> #REF! | ... V98: =V77*V4 -> #REF!
M99: =M78*M4 -> 23101.25 | N99: =N78*N4 -> 22659.063 | O99: =O78*O4 -> 22971.45 | P99: =P78*P4 -> 23476.51 | Q99: =Q78*Q4 -> 24185.182 | R99: =R78*R4 -> 25113.565 | S99: =S78*S4 -> 26283.516 | T99: =T78*T4 -> 27729.109 | ... V99: =V78*V4 -> 0
M100: =M79*M4 -> 20614.915 | N100: =N79*N4 -> 20220.32 | O100: =O79*O4 -> 20499.085 | P100: =P79*P4 -> 20949.787 | Q100: =Q79*Q4 -> 21582.186 | R100: =R79*R4 -> 22410.649 | S100: =S79*S4 -> 23454.68 | T100: =T79*T4 -> 24744.688 | ... V100: =V79*V4 -> 0

Sheet FCFF 
D2: Calculation Of Free Cash Flows
B3: 2015 | C3: 2016 | D3: 2017 | E3: 2018 | F3: 2019 | G3: 2020 | H3: 2021 | I3: 2022 | J3: 2023 | K3: 2024 | L3: 2025(UA) | M3: 2026 | N3: 2027 | O3: 2028 | P3: 2029 | Q3: 2030 | R3: 2031 | S3: 2032
A4: EBIT(1-tax) | B4: =FS_Forecast!B13*(1-FS_Forecast!B21) -> 5978.6253 | C4: =FS_Forecast!C13*(1-FS_Forecast!C21) -> 6321.1053 | D4: =FS_Forecast!D13*(1-FS_Forecast!D21) -> 7709.1705 | E4: =FS_Forecast!E13*(1-FS_Forecast!E21) -> 11738.359 | F4: =FS_Forecast!F13*(1-FS_Forecast!F21) -> 13469.23 | G4: =FS_Forecast!G13*(1-FS_Forecast!G21) -> 15588.383 | H4: =FS_Forecast!H13*(1-FS_Forecast!H21) -> 17033.287 | I4: =FS_Forecast!I13*(1-FS_Forecast!I21) -> 19051.369 | ... K4: =FS_Forecast!K13*(1-FS_Forecast!K21) -> 25724.566 | L4: =FS_Forecast!M13*(1-FS_Forecast!M21) -> 16568.467 | M4: =FS_Forecast!N13*(1-FS_Forecast!N21) -> 18501.273 | N4: =FS_Forecast!O13*(1-FS_Forecast!O21) -> 23268.276 | O4: =FS_Forecast!P13*(1-FS_Forecast!P21) -> 23779.862 | P4: =FS_Forecast!Q13*(1-FS_Forecast!Q21) -> 24497.691 | Q4: =FS_Forecast!R13*(1-FS_Forecast!R21) -> 25438.069 | R4: =FS_Forecast!S13*(1-FS_Forecast!S21) -> 26623.138 | S4: =FS_Forecast!T13*(1-FS_Forecast!T21) -> 28087.41
A5: (+) Depriciation | B5: =Financials!C11 -> 1693 | C5: =Financials!D11 -> 2055 | D5: =Financials!E11 -> 2245 | E5: =Financials!F11 -> 2428 | F5: =Financials!G11 -> 2720 | G5: =Financials!H11 -> 2891 | H5: =Financials!I11 -> 3103 | I5: =Financials!J11 -> 3400 | ... K5: =Financials!L11 -> 4099 | L5: 4361 | M5: =FS_Forecast!N11 -> 4658.9867 | N5: =FS_Forecast!O11 -> 4723.2174 | O5: =FS_Forecast!P11 -> 4827.064 | P5: =FS_Forecast!Q11 -> 4972.7758 | Q5: =FS_Forecast!R11 -> 5163.6628 | R5: =FS_Forecast!S11 -> 5404.2194 | S5: =FS_Forecast!T11 -> 5701.4514
A6: (-) Capex | B6: 1556 | C6: 1705 | D6: 2023 | E6: 2063 | F6: 2071 | G6: 2051 | H6: 2454 | I6: 2802 | J6: 3386 | K6: 3499 | L6: 3622 | M6: =$M$9*FS_Forecast!N4 -> 4163.8663 | N6: =$M$9*FS_Forecast!O4 -> 4221.2711 | O6: =$M$9*FS_Forecast!P4 -> 4314.0818 | P6: =$M$9*FS_Forecast!Q4 -> 4444.3084 | Q6: =$M$9*FS_Forecast!R4 -> 4614.9095 | R6: =$M$9*FS_Forecast!S4 -> 4829.9016 | S6: =$M$9*FS_Forecast!T4 -> 5095.5462
A7: Change in NWC | B7: =FS_Forecast!C41 -> 2235 | C7: =FS_Forecast!D41 -> -3166 | D7: =FS_Forecast!E41 -> -4553 | E7: =FS_Forecast!F41 -> -787 | F7: =FS_Forecast!G41 -> -2699 | G7: =FS_Forecast!H41 -> -5141 | H7: =FS_Forecast!I41 -> -3530 | I7: =FS_Forecast!J41 -> -7786 | ... S7: =FS_Forecast!T41 -> -3138.2335
A8: Free Cash Flows | B8: =B4+B5-B6-B7 -> 3880.6253 | C8: =C4+C5-C6-C7 -> 9837.1053 | D8: =D4+D5-D6-D7 -> 12484.171 | E8: =E4+E5-E6-E7 -> 12890.359 | F8: =F4+F5-F6-F7 -> 16817.23 | G8: =G4+G5-G6-G7 -> 21569.383 | H8: =H4+H5-H6-H7 -> 21212.287 | I8: =I4+I5-I6-I7 -> 27435.369 | ... S8: =S4+S5-S6-S7 -> 31831.549
B9: =B6/Financials!B4 -> 0.011925748 | C9: =C6/Financials!C4 -> 0.010852476 | D9: =D6/Financials!D4 -> 0.010944601 | E9: =E6/Financials!E4 -> 0.010255569 | F9: =F6/Financials!F4 -> 0.0091537125 | G9: =G6/Financials!G4 -> 0.0084697818 | H9: =H6/Financials!H4 -> 0.0095434023 | I9: =I6/Financials!I4 -> 0.0097427998 | ... K9: =K6/Financials!K4 -> 0.0094154813 | L9: =L6/FS_Forecast!M4 -> 0.0080926431 | M9: =IFERROR(__xludf.DUMMYFUNCTION("AVERAGE.WEIGHTED(B9:L9,B10:L10)"),0.009484889162893884) -> 0.0094848892
B10: 1 | C10: 2 | D10: 3 | E10: 4 | F10: 5 | G10: 6 | H10: 7 | I10: 8 | J10: 9 | K10: 10 | L10: 11
M11: 1 | N11: 2 | O11: 3 | P11: 4 | Q11: 5 | R11: 6 | S11: 7
M12: =M8/(1+$B$24)^M11 -> 21545.848 | N12: =N8/(1+$B$24)^N11 -> 20689.209 | O12: =O8/(1+$B$24)^O11 -> 21149.322 | P12: =P8/(1+$B$24)^P11 -> 20820.841 | Q12: =Q8/(1+$B$24)^Q11 -> 20650.775 | R12: =R8/(1+$B$24)^R11 -> 20634.489 | S12: =S8/(1+$B$24)^S11 -> 20782.543
F13: Terminal Growth Rate | H13: 0.02
A14: WACC Calculation | F14: 2032 FCF x (1+g) | H14: =S8*(1+H13) -> 32468.18 | J14: hjbjb
A15: Risk Free Rate | B15: 0.0414 | F15: Terminal value in 2027 | H15: =H14/(B24-H13) -> 758613.09 | J15: =K15-K13 -> 0
A16: Market Risk Premium | B16: 0.0638 | F16: Present Value of Terminal Value | H16: =H15/J18 -> 495291.92 | M16: =SUM(M12:S12) -> 146273.03
A17: Beta | B17: 0.43 | F17: Present Value of Projected Cash Flows | H17: =SUM(L12:U12) -> 146273.03
A18: Cost Of Equity | B18: =B15+(B17*B16) -> 0.068834 | F18: Total enterprise value (TEV) | H18: =SUM(H16:H17) -> 641564.95 | J18: =(1+B24)^S11 -> 1.5316484
A19: Value Of Equity | B19: =Sheet3!M4 -> 262693.6 | F19: Non Operating Assets | H19: =Financials!M42 -> 54251
A20: YTM | B20: 0.0534 | F20: Terminal value as % of TEV | H20: =H16/H18 -> 0.77200589
A21: Tax Rate | B21: 0.21
A22: Cost Of Debt | B22: =B20*(1-B21) -> 0.042186
A23: Value Of Debt | B23: =Sheet3!M5+H28 -> 76904 | F23: Valuation
A24: WACC | B24: =B26+B27 -> 0.062799394
H25: Perpetuity
A26: =B19/A30 -> 0.77354375 | B26: =A26*B18 -> 0.05324611 | F26: Enterprise value | H26: =H18+H19 -> 695815.95
A27: =B23/A30 -> 0.22645625 | B27: =B22*A27 -> 0.0095532835 | F27: Outstanding debt | H27: =Sheet3!M5+I27 -> 72359
F28: Short term Borrowings | H28: 4545
F29: Non controlling Interests | H29: 9933
A30: =B19+B23 -> 339597.6 | F30: Operating Lease | H30: 4889
F31: Equity value | H31: =H26-H27-H29-H30-H28 -> 604089.95
F32: Shares Outstanding | H32: 907.67
F33: Equity Value Per Share | H33: =H31/H32 -> 665.53918

Sheet Sheet3
B2: Adj Close
A3: 44256 | B3: 290 | C3: 6909.51 | E3: =SLOPE(H4:H263,I4:I263) -> 0.32298712
A4: 44287 | B4: 286.93 | C4: 6939.03 | H4: -0.0109 | I4: 0.0107 | K4: =4.08+0.323*(6) -> 6.018 | M4: =905.84*290 -> 262693.6
A5: 44317 | B5: 330.11 | C5: 6845.5 | E5: =COVAR(B3:B55,C3:C55) -> -51372.093 | H5: 0.0598 | I5: -0.0139 | K5: 3 | M5: 72359
A6: 44348 | B6: 329.77 | C6: 6849.09 | E6: =VAR(C3:C55) -> 975450.6 | H6: -0.0358 | I6: -0.001 | M6: =SUM(M4:M5) -> 335052.6
A7: 44378 | B7: 341.56 | C7: 6840.2 | H7: -0.1946 | I7: 0.0034
A8: 44409 | B8: 345.3 | C8: 6688.46 | H8: 0.0762 | I8: -0.0035 | M8: =M5/M4 -> 0.27545018
A9: 44440 | B9: 309.87 | C9: 6460.26 | F9: =COVAR(H4:H263,I4:I263) -> 0.00015750513 | H9: -0.0377 | I9: -0.0038 | K9: =(M4/M6)*K4 -> 4.718334 | M9: =(1-0.28)*M8 -> 0.19832413 | N9: =1+M9 -> 1.1983241
A10: 44470 | B10: 249.56 | C10: 6339.39 | F10: =VAR(I4:I263) -> 0.00048953426 | H10: 0.0225 | I10: 0.0157 | K10: =(M5/M6)*K5 -> 0.64788932 | N10: =0.323*N9 -> 0.38705869
A11: 44501 | B11: 311.97 | C11: 6204.95 | F11: =F9/F10 -> 0.32174486 | H11: 0.0138 | I11: -0.0103 | K11: =SUM(K9:K10) -> 5.3662233
A12: 44531 | B12: 301.91 | C12: 5911.69 | H12: 0.0135 | I12: 0.014
A13: 44562 | B13: 411.44 | C13: 5569.06 | H13: -0.0422 | I13: 0.001 | L13: =SLOPE(I4:I263,H4:H263) -> 0.073301228
A14: 44593 | B14: 523.75 | C14: 5611.85 | H14: 0.033 | I14: -0.0063
A15: 44621 | B15: 474.96 | C15: 5954.5 | H15: 0.0035 | I15: 0.0031
A16: 44652 | B16: 542.49 | C16: 6040.53 | H16: 0.0306 | I16: 0.0373
A17: 44682 | B17: 505.86 | C17: 5881.63 | H17: -0.0059 | I17: -0.0195
A18: 44713 | B18: 610.2 | C18: 6032.38 | H18: -0.0072 | I18: 0.0008
A19: 44743 | B19: 564.5 | C19: 5705.45 | H19: -0.0508 | I19: -0.0163
A20: 44774 | B20: 584.68 | C20: 5762.48 | H20: -0.0578 | I20: 0.0071
A21: 44805 | B21: 590.2 | C21: 5648.4 | H21: 0.0165 | I21: 0.0192
A22: 44835 | B22: 576.16 | C22: 5522.3 | H22: 0.0059 | I22: 0.017
A23: 44866 | B23: 509.26 | C23: 5460.48 | H23: -0.0158 | I23: -0.0243
A24: 44896 | B24: 495.37 | C24: 5277.51 | H24: 0.0468 | I24: 0.0109
A25: 44927 | B25: 483.7 | C25: 5035.69 | H25: 0.0219 | I25: -0.0031
... A62: 46054 | B62: 372.07 | C62: 3972.89 | H62: 0.015 | I62: -0.0194
H63: 0.0059 | I63: -0.0048
H64: 0.0197 | I64: 0.0067
H65: -0.0391 | I65: -0.0199
H66: -0.053 | I66: -0.0064
H67: -0.0993 | I67: 0.0096
H68: 0.0327 | I68: 0.0106
H69: -0.0023 | I69: 0.0168
H70: -0.0383 | I70: -0.0208
H71: 0.085 | I71: 0.0466
H72: 0.0053 | I72: -0.0137
H73: -0.0089 | I73: -0.0096
H74: -0.0476 | I74: 0.0085
... H263: 0.0448 | I263: 0.0081
